README.md
setup.py
cybertnetica.egg-info/PKG-INFO
cybertnetica.egg-info/SOURCES.txt
cybertnetica.egg-info/dependency_links.txt
cybertnetica.egg-info/requires.txt
cybertnetica.egg-info/top_level.txt
deployer/__init__.py
deployer/auto_deployer.py
util/__init__.py
util/logger.py
util/sftp.py
util/ssh.py