Metadata-Version: 2.1
Name: cybertnetica
Version: 0.0.1
Summary: automata for deployment
Home-page: https://github.com/roventine/cybertnetica
Author: roventine
Author-email: ukyotachibana@yeah.net
License: UNKNOWN
Platform: UNKNOWN
Classifier: Programming Language :: Python :: 3
Classifier: License :: OSI Approved :: MIT License
Classifier: Operating System :: OS Independent
Requires-Python: >=3.6
